eshipper_lib/__init__.py
eshipper_lib/error.py
eshipper_lib/quote_reply.py
eshipper_lib/quote_request.py
eshipper_lib/shipment_cancel_reply.py
eshipper_lib/shipment_cancel_request.py
eshipper_lib/shipping_reply.py
eshipper_lib/shipping_request.py
purplship/mappers/eshipper/__init__.py
purplship/mappers/eshipper/mapper.py
purplship/mappers/eshipper/proxy.py
purplship/mappers/eshipper/settings.py
purplship/providers/eshipper/__init__.py
purplship/providers/eshipper/error.py
purplship/providers/eshipper/quote.py
purplship/providers/eshipper/shipping.py
purplship/providers/eshipper/units.py
purplship/providers/eshipper/utils.py
purplship/providers/eshipper/void_shipment.py
purplship.eshipper-2022.2.dist-info/LICENSE
purplship.eshipper-2022.2.dist-info/WHEEL
purplship.eshipper-2022.2.dist-info/METADATA
purplship.eshipper-2022.2.dist-info/RECORD
